pytest_cagoule/__init__.py
pytest_cagoule/cmdline.py
pytest_cagoule/git_parser.py
pytest_cagoule/plugin.py
pytest_cagoule/select.py
pytest_cagoule-0.1.0.dist-info/DESCRIPTION.rst
pytest_cagoule-0.1.0.dist-info/entry_points.txt
pytest_cagoule-0.1.0.dist-info/METADATA
pytest_cagoule-0.1.0.dist-info/metadata.json
pytest_cagoule-0.1.0.dist-info/RECORD
pytest_cagoule-0.1.0.dist-info/top_level.txt
pytest_cagoule-0.1.0.dist-info/WHEEL
