Metadata-Version: 2.0
Name: pytest-cagoule
Version: 0.1.0
Summary: Pytest plugin to only run tests affected by changes
Home-page: https://github.com/davidszotten/pytest-cagoule
Author: David Szotten
Author-email: davidszotten@gmail.com
License: MIT
Platform: UNKNOWN
Classifier: Development Status :: 3 - Alpha
Classifier: Intended Audience :: Developers
Classifier: Topic :: Software Development :: Testing
Classifier: License :: OSI Approved :: MIT License
Classifier: Programming Language :: Python :: 2
Classifier: Programming Language :: Python :: 2.7
Classifier: Programming Language :: Python :: 3
Classifier: Programming Language :: Python :: 3.3
Requires-Dist: coverage
Requires-Dist: pytest
Requires-Dist: six
